{"cameraMode":{"drawMode":0,"name":"Shaded","section":"Shading Mode"},"sceneLighting":false,"audioPlay":false,"sceneViewState":{"m_AlwaysRefresh":false,"showFog":true,"showSkybox":false,"showFlares":true,"showImageEffects":true,"showParticleSystems":true,"showVisualEffectGraphs":true,"m_FxEnabled":true},"in2DMode":false,"pivot":{"x":0.0,"y":0.6010000109672546,"z":0.4830000102519989},"rotation":{"x":-0.128453329205513,"y":0.6716635227203369,"z":0.11997061967849732,"w":0.7196433544158936},"size":0.24494899809360505,"orthographic":false}